hekaos_text_insights/__init__.py
hekaos_text_insights/core.py
hekaos_text_insights/insights.py
hekaos_text_insights/keywords.py
hekaos_text_insights/readability.py
hekaos_text_insights-0.1.0.dist-info/licenses/LICENSE
hekaos_text_insights-0.1.0.dist-info/METADATA
hekaos_text_insights-0.1.0.dist-info/WHEEL
hekaos_text_insights-0.1.0.dist-info/top_level.txt
hekaos_text_insights-0.1.0.dist-info/RECORD
