Metadata-Version: 2.4
Name: hekaos-text-insights
Version: 0.1.0
Summary: Lightweight text analysis toolkit for extracting keywords, insights, and readability metrics
Author-email: Hekaos <digital@hekaos.com>
Maintainer-email: Hekaos <digital@hekaos.com>
License: MIT
Project-URL: Homepage, https://github.com/preet893700/hekaos-text-insights
Project-URL: Repository, https://github.com/preet893700/hekaos-text-insights
Project-URL: Issues, https://github.com/preet893700/hekaos-text-insights/issues
Keywords: text-analysis,nlp,keywords,readability,insights
Classifier: Development Status :: 4 - Beta
Classifier: Intended Audience :: Developers
Classifier: License :: OSI Approved :: MIT License
Classifier: Programming Language :: Python :: 3
Classifier: Programming Language :: Python :: 3.8
Classifier: Programming Language :: Python :: 3.9
Classifier: Programming Language :: Python :: 3.10
Classifier: Programming Language :: Python :: 3.11
Classifier: Programming Language :: Python :: 3.12
Classifier: Topic :: Text Processing :: Linguistic
Requires-Python: >=3.8
License-File: LICENSE
Dynamic: license-file
